ingrida_data_kup/__init__.py
ingrida_data_kup/main.py
ingrida_data_kup-0.1.0.dist-info/METADATA
ingrida_data_kup-0.1.0.dist-info/WHEEL
ingrida_data_kup-0.1.0.dist-info/RECORD
